nrobust/__init__.py
nrobust/figures.py
nrobust/models.py
nrobust/prototypes.py
nrobust/replication_data_prep.py
nrobust/utils.py
nrobust-0.0.1.dev4.dist-info/LICENSE
nrobust-0.0.1.dev4.dist-info/METADATA
nrobust-0.0.1.dev4.dist-info/WHEEL
nrobust-0.0.1.dev4.dist-info/top_level.txt
nrobust-0.0.1.dev4.dist-info/RECORD
